{
    "swagger": "2.0",
    "info": {
        "contact": {}
    },
    "paths": {
        "/api/v1/login": {
            "post": {
                "produces": [
                    "application/json"
                ],
                "summary": "Login",
                "operationId": "login",
                "parameters": [
                    {
                        "description": "login request",
                        "name": "req",
                        "in": "body",
                        "required": true,
                        "schema": {
                            "$ref": "#/definitions/auth.LoginRequest"
                        }
                    }
                ],
                "responses": {
                    "200": {
                        "description": "OK",
                        "schema": {
                            "$ref": "#/definitions/auth.LoginResponse"
                        }
                    }
                }
            }
        },
        "/api/v1/shift": {
            "post": {
                "produces": [
                    "application/json"
                ],
                "summary": "Create new shift",
                "operationId": "create-new-shift",
                "parameters": [
                    {
                        "description": "create shift request",
                        "name": "req",
                        "in": "body",
                        "required": true,
                        "schema": {
                            "$ref": "#/definitions/models.CreateShiftRequest"
                        }
                    }
                ],
                "responses": {
                    "200": {
                        "description": "OK",
                        "schema": {
                            "$ref": "#/definitions/models.CreateShiftResponse"
                        }
                    }
                }
            },
            "delete": {
                "produces": [
                    "application/json"
                ],
                "summary": "Delete shift",
                "operationId": "delete-shift",
                "parameters": [
                    {
                        "description": "delete shift request",
                        "name": "req",
                        "in": "body",
                        "required": true,
                        "schema": {
                            "$ref": "#/definitions/models.DeleteShiftRequest"
                        }
                    }
                ],
                "responses": {
                    "200": {
                        "description": "OK",
                        "schema": {
                            "$ref": "#/definitions/models.DeleteShiftResponse"
                        }
                    }
                }
            },
            "patch": {
                "produces": [
                    "application/json"
                ],
                "summary": "Update shift",
                "operationId": "update-shift",
                "parameters": [
                    {
                        "description": "update shift request",
                        "name": "req",
                        "in": "body",
                        "required": true,
                        "schema": {
                            "$ref": "#/definitions/models.UpdateShiftRequest"
                        }
                    }
                ],
                "responses": {
                    "200": {
                        "description": "OK",
                        "schema": {
                            "$ref": "#/definitions/models.UpdateShiftResponse"
                        }
                    }
                }
            }
        },
        "/api/v1/signup": {
            "post": {
                "produces": [
                    "application/json"
                ],
                "summary": "Create a new user",
                "operationId": "create-a-new-user",
                "parameters": [
                    {
                        "description": "create user request",
                        "name": "req",
                        "in": "body",
                        "required": true,
                        "schema": {
                            "$ref": "#/definitions/models.CreateUserRequest"
                        }
                    }
                ],
                "responses": {
                    "200": {
                        "description": "OK",
                        "schema": {
                            "$ref": "#/definitions/models.CreateUserResponse"
                        }
                    }
                }
            }
        },
        "/api/v1/user": {
            "delete": {
                "produces": [
                    "application/json"
                ],
                "summary": "Delete user",
                "operationId": "delete-user",
                "parameters": [
                    {
                        "description": "delete user request",
                        "name": "req",
                        "in": "body",
                        "required": true,
                        "schema": {
                            "$ref": "#/definitions/models.DeleteUserRequest"
                        }
                    }
                ],
                "responses": {
                    "200": {
                        "description": "OK",
                        "schema": {
                            "$ref": "#/definitions/models.DeleteUserResponse"
                        }
                    }
                }
            }
        },
        "/api/v1/user/permission": {
            "put": {
                "produces": [
                    "application/json"
                ],
                "summary": "Update user permission level",
                "operationId": "update-user-permission-level",
                "parameters": [
                    {
                        "description": "update user permission request",
                        "name": "req",
                        "in": "body",
                        "required": true,
                        "schema": {
                            "$ref": "#/definitions/models.UpdateUserPermissionLevelRequest"
                        }
                    }
                ],
                "responses": {
                    "200": {
                        "description": "OK",
                        "schema": {
                            "$ref": "#/definitions/models.UpdateUserPermissionLevelResponse"
                        }
                    }
                }
            }
        }
    },
    "definitions": {
        "auth.LoginRequest": {
            "type": "object",
            "properties": {
                "email": {
                    "type": "string"
                },
                "password": {
                    "type": "string"
                }
            }
        },
        "auth.LoginResponse": {
            "type": "object",
            "properties": {
                "base_response": {
                    "$ref": "#/definitions/models.BaseResponse"
                },
                "token": {
                    "type": "string"
                }
            }
        },
        "models.BaseResponse": {
            "type": "object",
            "properties": {
                "error_msg": {
                    "type": "string"
                },
                "error_stack": {
                    "type": "array",
                    "items": {
                        "type": "string"
                    }
                },
                "error_type": {
                    "type": "string"
                },
                "success": {
                    "type": "boolean"
                }
            }
        },
        "models.CreateShiftRequest": {
            "type": "object",
            "properties": {
                "shift_length_in_hours": {
                    "type": "number"
                },
                "user_email": {
                    "type": "string"
                },
                "work_date": {
                    "type": "string"
                }
            }
        },
        "models.CreateShiftResponse": {
            "type": "object",
            "properties": {
                "base_response": {
                    "$ref": "#/definitions/models.BaseResponse"
                },
                "schedule": {
                    "$ref": "#/definitions/models.Shift"
                }
            }
        },
        "models.CreateUserRequest": {
            "type": "object",
            "properties": {
                "email": {
                    "type": "string"
                },
                "first_name": {
                    "type": "string"
                },
                "last_name": {
                    "type": "string"
                },
                "password": {
                    "type": "string"
                }
            }
        },
        "models.CreateUserResponse": {
            "type": "object",
            "properties": {
                "base_response": {
                    "$ref": "#/definitions/models.BaseResponse"
                },
                "user": {
                    "$ref": "#/definitions/models.User"
                }
            }
        },
        "models.DeleteShiftRequest": {
            "type": "object",
            "properties": {
                "shift_uid": {
                    "type": "string"
                }
            }
        },
        "models.DeleteShiftResponse": {
            "type": "object",
            "properties": {
                "base_response": {
                    "$ref": "#/definitions/models.BaseResponse"
                },
                "shift": {
                    "$ref": "#/definitions/models.Shift"
                }
            }
        },
        "models.DeleteUserRequest": {
            "type": "object",
            "properties": {
                "email": {
                    "type": "string"
                }
            }
        },
        "models.DeleteUserResponse": {
            "type": "object",
            "properties": {
                "base_response": {
                    "$ref": "#/definitions/models.BaseResponse"
                },
                "user": {
                    "$ref": "#/definitions/models.User"
                }
            }
        },
        "models.Shift": {
            "type": "object",
            "properties": {
                "created": {
                    "type": "string"
                },
                "deleted": {
                    "type": "string"
                },
                "id": {
                    "type": "integer"
                },
                "shift_length_in_hours": {
                    "type": "number"
                },
                "uid": {
                    "type": "string"
                },
                "updated": {
                    "type": "string"
                },
                "user_id": {
                    "type": "integer"
                },
                "work_date": {
                    "type": "string"
                }
            }
        },
        "models.UpdateShiftRequest": {
            "type": "object",
            "properties": {
                "assigned_user_email": {
                    "type": "string"
                },
                "shift_length_in_hours": {
                    "type": "number"
                },
                "shift_uid": {
                    "type": "string"
                },
                "work_date": {
                    "type": "string"
                }
            }
        },
        "models.UpdateShiftResponse": {
            "type": "object",
            "properties": {
                "base_response": {
                    "$ref": "#/definitions/models.BaseResponse"
                },
                "shift": {
                    "$ref": "#/definitions/models.Shift"
                }
            }
        },
        "models.UpdateUserPermissionLevelRequest": {
            "type": "object",
            "properties": {
                "email": {
                    "type": "string"
                },
                "permission_level": {
                    "type": "string"
                }
            }
        },
        "models.UpdateUserPermissionLevelResponse": {
            "type": "object",
            "properties": {
                "base_response": {
                    "$ref": "#/definitions/models.BaseResponse"
                },
                "user": {
                    "$ref": "#/definitions/models.User"
                }
            }
        },
        "models.User": {
            "type": "object",
            "properties": {
                "created": {
                    "type": "string"
                },
                "deleted": {
                    "type": "string"
                },
                "email": {
                    "type": "string"
                },
                "first_name": {
                    "type": "string"
                },
                "id": {
                    "type": "integer"
                },
                "last_name": {
                    "type": "string"
                },
                "password": {
                    "type": "string"
                },
                "type": {
                    "type": "string"
                },
                "uid": {
                    "type": "string"
                },
                "updated": {
                    "type": "string"
                }
            }
        }
    }
}